llm_code/__init__.py
llm_code/db.py
llm_code/llm_code.py
llm_code/templates.py
prompts/coding/system.toml
prompts/coding/user/input.toml
prompts/coding/user/simple.toml
llm_code-0.8.0.dist-info/LICENSE
llm_code-0.8.0.dist-info/METADATA
llm_code-0.8.0.dist-info/WHEEL
llm_code-0.8.0.dist-info/entry_points.txt
llm_code-0.8.0.dist-info/RECORD
