Metadata-Version: 2.1
Name: llm-code
Version: 0.8.0
Summary: An OpenAI LLM based CLI coding assistant.
Home-page: https://github.com/radoshi/llm-code
License: MIT
Keywords: openai,llm,cli,coding,assistant
Author: Rushabh Doshi
Author-email: radoshi+pypi@gmail.com
Requires-Python: >=3.11,<4.0
Classifier: Development Status :: 3 - Alpha
Classifier: Environment :: Console
Classifier: License :: OSI Approved :: MIT License
Classifier: Programming Language :: Python :: 3
Classifier: Programming Language :: Python :: 3.11
Classifier: Programming Language :: Python :: 3.12
Classifier: Topic :: Software Development
Classifier: Topic :: Software Development :: Code Generators
Requires-Dist: click (>=8.1.3,<9.0.0)
Requires-Dist: openai (>=0.27.6,<0.28.0)
Requires-Dist: pydantic[dotenv] (>=1.10.7,<2.0.0)
Requires-Dist: pyperclip (>=1.8.2,<2.0.0)
Requires-Dist: rich (>=13.3.5,<14.0.0)
Requires-Dist: sqlalchemy (>=2.0.15,<3.0.0)
Requires-Dist: tomli (>=2.0.1,<3.0.0)
Project-URL: Repository, https://github.com/radoshi/llm-code
